threadman/__init__.py
threadman/main.py
threadman/py.typed
threadman-0.1.0.dist-info/METADATA
threadman-0.1.0.dist-info/WHEEL
threadman-0.1.0.dist-info/licenses/LICENSE
threadman-0.1.0.dist-info/RECORD
