Metadata-Version: 2.4
Name: threadman
Version: 0.1.0
Summary: A simple thread manager for Python
Project-URL: homepage, https://github.com/your-username/threadman
Author-email: Ryan Punt <ryan@mirum.org>
License-File: LICENSE
Classifier: License :: OSI Approved :: MIT License
Classifier: Operating System :: OS Independent
Classifier: Programming Language :: Python :: 3
Classifier: Programming Language :: Python :: 3.9
Classifier: Programming Language :: Python :: 3.10
Classifier: Programming Language :: Python :: 3.11
Classifier: Programming Language :: Python :: 3.12
Classifier: Topic :: Software Development :: Libraries :: Python Modules
Requires-Python: >=3.9
Requires-Dist: tqdm>=4.67.1
